bornly.py
bornly/__init__.py
bornly/_seaborn/__init__.py
bornly/_seaborn/setup.py
bornly/_seaborn/seaborn/__init__.py
bornly/_seaborn/seaborn/_core.py
bornly/_seaborn/seaborn/_decorators.py
bornly/_seaborn/seaborn/_docstrings.py
bornly/_seaborn/seaborn/_statistics.py
bornly/_seaborn/seaborn/_testing.py
bornly/_seaborn/seaborn/algorithms.py
bornly/_seaborn/seaborn/axisgrid.py
bornly/_seaborn/seaborn/categorical.py
bornly/_seaborn/seaborn/cm.py
bornly/_seaborn/seaborn/conftest.py
bornly/_seaborn/seaborn/distributions.py
bornly/_seaborn/seaborn/matrix.py
bornly/_seaborn/seaborn/miscplot.py
bornly/_seaborn/seaborn/palettes.py
bornly/_seaborn/seaborn/rcmod.py
bornly/_seaborn/seaborn/regression.py
bornly/_seaborn/seaborn/relational.py
bornly/_seaborn/seaborn/utils.py
bornly/_seaborn/seaborn/widgets.py
bornly/_seaborn/seaborn/colors/__init__.py
bornly/_seaborn/seaborn/colors/crayons.py
bornly/_seaborn/seaborn/colors/xkcd_rgb.py
bornly/_seaborn/seaborn/external/__init__.py
bornly/_seaborn/seaborn/external/docscrape.py
bornly/_seaborn/seaborn/external/husl.py
bornly/_seaborn/seaborn/external/kde.py
bornly/_seaborn/seaborn/external/version.py
bornly/_seaborn/seaborn/tests/__init__.py
bornly/_seaborn/seaborn/tests/test_algorithms.py
bornly/_seaborn/seaborn/tests/test_axisgrid.py
bornly/_seaborn/seaborn/tests/test_categorical.py
bornly/_seaborn/seaborn/tests/test_core.py
bornly/_seaborn/seaborn/tests/test_decorators.py
bornly/_seaborn/seaborn/tests/test_distributions.py
bornly/_seaborn/seaborn/tests/test_docstrings.py
bornly/_seaborn/seaborn/tests/test_matrix.py
bornly/_seaborn/seaborn/tests/test_miscplot.py
bornly/_seaborn/seaborn/tests/test_palettes.py
bornly/_seaborn/seaborn/tests/test_rcmod.py
bornly/_seaborn/seaborn/tests/test_regression.py
bornly/_seaborn/seaborn/tests/test_relational.py
bornly/_seaborn/seaborn/tests/test_statistics.py
bornly/_seaborn/seaborn/tests/test_utils.py
bornly-0.3.0.dist-info/LICENSE
bornly-0.3.0.dist-info/METADATA
bornly-0.3.0.dist-info/WHEEL
bornly-0.3.0.dist-info/top_level.txt
bornly-0.3.0.dist-info/RECORD
