Metadata-Version: 2.1
Name: bornly
Version: 0.3.0
Summary: Seaborn-like API for some plotly plots
Home-page: https://github.com/MarcoGorelli/bornly
Author: Marco Gorelli
License: MIT
Platform: UNKNOWN
Classifier: License :: OSI Approved :: MIT License
Classifier: Programming Language :: Python :: 3
Classifier: Programming Language :: Python :: 3 :: Only
Classifier: Programming Language :: Python :: 3.7
Classifier: Programming Language :: Python :: 3.8
Classifier: Programming Language :: Python :: 3.9
Classifier: Programming Language :: Python :: 3.10
Requires-Python: >=3.7.0
License-File: LICENSE
Requires-Dist: pandas
Requires-Dist: plotly
Requires-Dist: matplotlib
Requires-Dist: scipy
